{"0": "Docs site app", "1": "API generation script", "2": "RayKim SDK core", "3": "Project concept map", "4": "Nano SDK core", "5": "Playground runtime UI", "6": "Docs UI architecture", "7": "Docs package dependencies", "8": "API and changes docs", "9": "Docs pipeline planning", "10": "TypeScript docs config", "11": "Scenario schema cases", "12": "Scenario schema fields", "13": "Nano SDK features", "14": "Docs translation script", "15": "Troubleshooting guides", "16": "Inference tutorial docs", "17": "Sync playground scenario", "18": "Migration guide docs", "19": "Scenario validity schema", "20": "Docs workflow concepts", "21": "Docs automation stack", "22": "Playground validation script", "23": "Output expectation schema", "24": "Rust Python bindings", "25": "Rust memory wrapper", "26": "Scenario metadata schema", "27": "Snippet validation flow", "28": "Exception schema defs", "29": "Locked output schema", "30": "MDX docs stack", "31": "Scenario schema root", "32": "Exception message schema", "33": "SDK README docs", "34": "Scenario explanations schema", "35": "Scenario cases schema", "36": "Scenario control schema", "37": "Snippet extraction script", "38": "Release notes docs", "39": "Next.js MDX config", "40": "Scenario id schema", "41": "Length limit schema", "42": "Allowed values schema", "43": "Scenario page schema", "44": "Scenario runtime schema", "45": "Scenario template schema", "46": "Scenario title schema", "47": "Playground worker runtime", "48": "Migration section docs", "49": "SDK bundle script", "50": "Troubleshooting section docs", "51": "Generic typing node", "52": "Device memory abstraction", "53": "MDX component hook", "54": "Next env types", "55": "PostCSS config", "56": "Tailwind config", "57": "Locale home page", "58": "Python package metadata", "59": "Test package init", "60": "Shadcn UI library"}